{
	"earlylc22zyos_forGene":{
		"name":"earlylc22zyos_forGene",
		"sources":[
			{
				"name":"MOSFiT paper",
				"alias":"1"
			}
		],
		"alias":[
			{
				"value":"earlylc22zyos_forGene",
				"source":"1"
			}
		],
		"redshift":[
			{
				"value":"0.033",
				"source":"1"
			}
		],
		"photometry":[
			{
				"time":"58219.307",
				"band":"r",
				"e_magnitude":"0.331960515",
				"magnitude":"20.51284909",
				"system":"AB",
				"u_time":"MJD",
				"source":"1"
			},
			{
				"time":"58284.268",
				"band":"g",
				"e_magnitude":"0.351337989",
				"magnitude":"21.86641491",
				"system":"AB",
				"u_time":"MJD",
				"source":"1"
			},
			{
				"time":"58878.546",
				"band":"o",
				"e_magnitude":"0.353488671",
				"magnitude":"21.11635983",
				"system":"AB",
				"u_time":"MJD",
				"source":"1"
			},
			{
				"time":"58884.614",
				"band":"c",
				"e_magnitude":"0.30860435",
				"magnitude":"21.38235502",
				"system":"AB",
				"u_time":"MJD",
				"source":"1"
			},
			{
				"time":"58899.487",
				"band":"r",
				"e_magnitude":"0.353623766",
				"magnitude":"21.63136073",
				"system":"AB",
				"u_time":"MJD",
				"source":"1"
			},
			{
				"time":"58956.437",
				"band":"c",
				"e_magnitude":"0.316372627",
				"magnitude":"21.10417491",
				"system":"AB",
				"u_time":"MJD",
				"source":"1"
			},
			{
				"time":"59323.373",
				"band":"r",
				"e_magnitude":"0.351143315",
				"magnitude":"21.54355792",
				"system":"AB",
				"u_time":"MJD",
				"source":"1"
			},
			{
				"time":"59378.338",
				"band":"c",
				"e_magnitude":"0.361456968",
				"magnitude":"21.64185523",
				"system":"AB",
				"u_time":"MJD",
				"source":"1"
			},
			{
				"time":"59386.301",
				"band":"g",
				"e_magnitude":"0.280602117",
				"magnitude":"20.45347551",
				"system":"AB",
				"u_time":"MJD",
				"source":"1"
			},
			{
				"time":"59671.414",
				"band":"c",
				"e_magnitude":"0.281539393",
				"magnitude":"20.61147366",
				"system":"AB",
				"u_time":"MJD",
				"source":"1"
			},
			{
				"time":"59672.32",
				"band":"g",
				"e_magnitude":"0.263625897",
				"magnitude":"21.6987157",
				"system":"AB",
				"u_time":"MJD",
				"source":"1"
			},
			{
				"time":"59675.222",
				"band":"r",
				"e_magnitude":"0.28492586",
				"magnitude":"20.92709905",
				"system":"AB",
				"u_time":"MJD",
				"source":"1"
			},
			{
				"time":"59675.223",
				"band":"r",
				"e_magnitude":"0.337536351",
				"magnitude":"21.11588646",
				"system":"AB",
				"u_time":"MJD",
				"source":"1"
			},
			{
				"time":"59675.344",
				"band":"r",
				"e_magnitude":"0.12569293",
				"magnitude":"20.59503538",
				"system":"AB",
				"u_time":"MJD",
				"source":"1"
			},
			{
				"time":"59675.366",
				"band":"g",
				"e_magnitude":"0.19272318",
				"magnitude":"21.18909517",
				"system":"AB",
				"u_time":"MJD",
				"source":"1"
			},
			{
				"time":"59675.382",
				"band":"g",
				"e_magnitude":"0.200878704",
				"magnitude":"20.95149654",
				"system":"AB",
				"u_time":"MJD",
				"source":"1"
			},
			{
				"time":"59676.3",
				"band":"g",
				"e_magnitude":"0.250668583",
				"magnitude":"20.80254288",
				"system":"AB",
				"u_time":"MJD",
				"source":"1"
			},
			{
				"time":"59676.451",
				"band":"r",
				"e_magnitude":"0.306275294",
				"magnitude":"20.56025729",
				"system":"AB",
				"u_time":"MJD",
				"source":"1"
			},
			{
				"time":"59676.485",
				"band":"r",
				"e_magnitude":"0.204360309",
				"magnitude":"20.11212619",
				"system":"AB",
				"u_time":"MJD",
				"source":"1"
			},
			{
				"time":"59677.288",
				"band":"i",
				"e_magnitude":"0.306167922",
				"magnitude":"20.66568934",
				"system":"AB",
				"u_time":"MJD",
				"source":"1"
			},
			{
				"time":"59677.31",
				"band":"g",
				"e_magnitude":"0.253779021",
				"magnitude":"20.79179768",
				"system":"AB",
				"u_time":"MJD",
				"source":"1"
			},
			{
				"time":"59677.323",
				"band":"g",
				"e_magnitude":"0.159399191",
				"magnitude":"20.46650251",
				"system":"AB",
				"u_time":"MJD",
				"source":"1"
			},
			{
				"time":"59677.323",
				"band":"g",
				"e_magnitude":"0.219041294",
				"magnitude":"20.55947234",
				"system":"AB",
				"u_time":"MJD",
				"source":"1"
			},
			{
				"time":"59677.345",
				"band":"g",
				"e_magnitude":"0.254547212",
				"magnitude":"20.92004968",
				"system":"AB",
				"u_time":"MJD",
				"source":"1"
			},
			{
				"time":"59677.374",
				"band":"r",
				"e_magnitude":"0.150904775",
				"magnitude":"20.40455553",
				"system":"AB",
				"u_time":"MJD",
				"source":"1"
			},
			{
				"time":"59677.386",
				"band":"r",
				"e_magnitude":"0.159450291",
				"magnitude":"20.38895006",
				"system":"AB",
				"u_time":"MJD",
				"source":"1"
			},
			{
				"time":"59677.413",
				"band":"r",
				"e_magnitude":"0.158977362",
				"magnitude":"20.42991832",
				"system":"AB",
				"u_time":"MJD",
				"source":"1"
			},
			{
				"time":"59677.444",
				"band":"o",
				"e_magnitude":"0.327871811",
				"magnitude":"20.57257622",
				"system":"AB",
				"u_time":"MJD",
				"source":"1"
			},
			{
				"time":"59678.332",
				"band":"g",
				"e_magnitude":"0.114440144",
				"magnitude":"20.09324729",
				"system":"AB",
				"u_time":"MJD",
				"source":"1"
			},
			{
				"time":"59678.391",
				"band":"r",
				"e_magnitude":"0.107874893",
				"magnitude":"19.94704339",
				"system":"AB",
				"u_time":"MJD",
				"source":"1"
			},
			{
				"time":"59678.471",
				"band":"r",
				"e_magnitude":"0.134392249",
				"magnitude":"20.15308844",
				"system":"AB",
				"u_time":"MJD",
				"source":"1"
			},
			{
				"time":"59678.485",
				"band":"g",
				"e_magnitude":"0.111744166",
				"magnitude":"20.04053886",
				"system":"AB",
				"u_time":"MJD",
				"source":"1"
			},
			{
				"time":"59679.216",
				"band":"r",
				"e_magnitude":"0.125769591",
				"magnitude":"19.82966933",
				"system":"AB",
				"u_time":"MJD",
				"source":"1"
			},
			{
				"time":"59679.238",
				"band":"r",
				"e_magnitude":"0.101131391",
				"magnitude":"19.75259",
				"system":"AB",
				"u_time":"MJD",
				"source":"1"
			},
			{
				"time":"59679.238",
				"band":"r",
				"e_magnitude":"0.1326553",
				"magnitude":"19.83947924",
				"system":"AB",
				"u_time":"MJD",
				"source":"1"
			},
			{
				"time":"59679.279",
				"band":"g",
				"e_magnitude":"0.117652843",
				"magnitude":"19.94029513",
				"system":"AB",
				"u_time":"MJD",
				"source":"1"
			},
			{
				"time":"59679.289",
				"band":"g",
				"e_magnitude":"0.11302067",
				"magnitude":"19.843249",
				"system":"AB",
				"u_time":"MJD",
				"source":"1"
			},
			{
				"time":"59679.301",
				"band":"g",
				"e_magnitude":"0.109338049",
				"magnitude":"20.02398282",
				"system":"AB",
				"u_time":"MJD",
				"source":"1"
			},
			{
				"time":"59679.319",
				"band":"g",
				"e_magnitude":"0.108415321",
				"magnitude":"19.89893251",
				"system":"AB",
				"u_time":"MJD",
				"source":"1"
			},
			{
				"time":"59679.396",
				"band":"r",
				"e_magnitude":"0.107776069",
				"magnitude":"19.90881559",
				"system":"AB",
				"u_time":"MJD",
				"source":"1"
			},
			{
				"time":"59679.439",
				"band":"c",
				"e_magnitude":"0.268475431",
				"magnitude":"20.02153201",
				"system":"AB",
				"u_time":"MJD",
				"source":"1"
			},
			{
				"time":"59680.276",
				"band":"i",
				"e_magnitude":"0.209901064",
				"magnitude":"19.79533294",
				"system":"AB",
				"u_time":"MJD",
				"source":"1"
			},
			{
				"time":"59680.344",
				"band":"r",
				"e_magnitude":"0.120620265",
				"magnitude":"19.64506308",
				"system":"AB",
				"u_time":"MJD",
				"source":"1"
			},
			{
				"time":"59680.344",
				"band":"r",
				"e_magnitude":"0.125631487",
				"magnitude":"19.75212296",
				"system":"AB",
				"u_time":"MJD",
				"source":"1"
			},
			{
				"time":"59681.502",
				"band":"o",
				"e_magnitude":"0.248260063",
				"magnitude":"19.71123651",
				"system":"AB",
				"u_time":"MJD",
				"source":"1"
			},
			{
				"time":"59682.195",
				"band":"g",
				"e_magnitude":"0.178306804",
				"magnitude":"19.43239442",
				"system":"AB",
				"u_time":"MJD",
				"source":"1"
			},
			{
				"time":"59682.222",
				"band":"g",
				"e_magnitude":"0.149179187",
				"magnitude":"19.64611345",
				"system":"AB",
				"u_time":"MJD",
				"source":"1"
			},
			{
				"time":"59682.223",
				"band":"g",
				"e_magnitude":"0.18129838",
				"magnitude":"19.60634765",
				"system":"AB",
				"u_time":"MJD",
				"source":"1"
			},
			{
				"time":"59682.269",
				"band":"i",
				"e_magnitude":"0.360113823",
				"magnitude":"20.18282595",
				"system":"AB",
				"u_time":"MJD",
				"source":"1"
			},
			{
				"time":"59682.28",
				"band":"r",
				"e_magnitude":"0.111013696",
				"magnitude":"19.34932261",
				"system":"AB",
				"u_time":"MJD",
				"source":"1"
			},
			{
				"time":"59682.28",
				"band":"r",
				"e_magnitude":"0.097121993",
				"magnitude":"19.5324462",
				"system":"AB",
				"u_time":"MJD",
				"source":"1"
			},
			{
				"time":"59682.349",
				"band":"r",
				"e_magnitude":"0.106805299",
				"magnitude":"19.49189777",
				"system":"AB",
				"u_time":"MJD",
				"source":"1"
			},
			{
				"time":"59682.35",
				"band":"r",
				"e_magnitude":"0.12866021",
				"magnitude":"19.59378916",
				"system":"AB",
				"u_time":"MJD",
				"source":"1"
			},
			{
				"time":"59682.364",
				"band":"r",
				"e_magnitude":"0.159578613",
				"magnitude":"19.763823",
				"system":"AB",
				"u_time":"MJD",
				"source":"1"
			},
			{
				"time":"59682.367",
				"band":"r",
				"e_magnitude":"0.10710183",
				"magnitude":"19.48030245",
				"system":"AB",
				"u_time":"MJD",
				"source":"1"
			},
			{
				"time":"59682.404",
				"band":"g",
				"e_magnitude":"0.134870909",
				"magnitude":"19.51226226",
				"system":"AB",
				"u_time":"MJD",
				"source":"1"
			},
			{
				"time":"59682.408",
				"band":"g",
				"e_magnitude":"0.137000226",
				"magnitude":"19.61107753",
				"system":"AB",
				"u_time":"MJD",
				"source":"1"
			},
			{
				"time":"59682.426",
				"band":"o",
				"e_magnitude":"0.122741255",
				"magnitude":"19.54580753",
				"system":"AB",
				"u_time":"MJD",
				"source":"1"
			},
			{
				"time":"59683.249",
				"band":"r",
				"e_magnitude":"0.101573988",
				"magnitude":"19.44706285",
				"system":"AB",
				"u_time":"MJD",
				"source":"1"
			},
			{
				"time":"59683.25",
				"band":"r",
				"e_magnitude":"0.117211795",
				"magnitude":"19.43065722",
				"system":"AB",
				"u_time":"MJD",
				"source":"1"
			},
			{
				"time":"59683.258",
				"band":"g",
				"e_magnitude":"0.147440366",
				"magnitude":"19.39649701",
				"system":"AB",
				"u_time":"MJD",
				"source":"1"
			},
			{
				"time":"59683.291",
				"band":"g",
				"e_magnitude":"0.134522147",
				"magnitude":"19.49525148",
				"system":"AB",
				"u_time":"MJD",
				"source":"1"
			},
			{
				"time":"59683.329",
				"band":"i",
				"e_magnitude":"0.169123288",
				"magnitude":"19.56385471",
				"system":"AB",
				"u_time":"MJD",
				"source":"1"
			},
			{
				"time":"59683.412",
				"band":"r",
				"e_magnitude":"0.07904887",
				"magnitude":"19.30883853",
				"system":"AB",
				"u_time":"MJD",
				"source":"1"
			},
			{
				"time":"59683.474",
				"band":"o",
				"e_magnitude":"0.343580643",
				"magnitude":"20.29779869",
				"system":"AB",
				"u_time":"MJD",
				"source":"1"
			},
			{
				"time":"59683.479",
				"band":"g",
				"e_magnitude":"0.100975348",
				"magnitude":"19.46432529",
				"system":"AB",
				"u_time":"MJD",
				"source":"1"
			},
			{
				"time":"59684.24",
				"band":"r",
				"e_magnitude":"0.148167917",
				"magnitude":"19.30520555",
				"system":"AB",
				"u_time":"MJD",
				"source":"1"
			},
			{
				"time":"59684.258",
				"band":"g",
				"e_magnitude":"0.207072073",
				"magnitude":"19.45400152",
				"system":"AB",
				"u_time":"MJD",
				"source":"1"
			},
			{
				"time":"59684.288",
				"band":"g",
				"e_magnitude":"0.134989595",
				"magnitude":"19.35433384",
				"system":"AB",
				"u_time":"MJD",
				"source":"1"
			},
			{
				"time":"59684.305",
				"band":"g",
				"e_magnitude":"0.183044198",
				"magnitude":"19.40060806",
				"system":"AB",
				"u_time":"MJD",
				"source":"1"
			},
			{
				"time":"59684.305",
				"band":"g",
				"e_magnitude":"0.154817492",
				"magnitude":"19.44074973",
				"system":"AB",
				"u_time":"MJD",
				"source":"1"
			},
			{
				"time":"59684.33",
				"band":"r",
				"e_magnitude":"0.090786696",
				"magnitude":"19.29627318",
				"system":"AB",
				"u_time":"MJD",
				"source":"1"
			},
			{
				"time":"59684.349",
				"band":"r",
				"e_magnitude":"0.117191383",
				"magnitude":"19.42444643",
				"system":"AB",
				"u_time":"MJD",
				"source":"1"
			},
			{
				"time":"59684.399",
				"band":"r",
				"e_magnitude":"0.099976752",
				"magnitude":"19.29054748",
				"system":"AB",
				"u_time":"MJD",
				"source":"1"
			},
			{
				"time":"59684.4",
				"band":"r",
				"e_magnitude":"0.097126037",
				"magnitude":"19.36410826",
				"system":"AB",
				"u_time":"MJD",
				"source":"1"
			},
			{
				"time":"59684.435",
				"band":"r",
				"e_magnitude":"0.134777107",
				"magnitude":"19.35681014",
				"system":"AB",
				"u_time":"MJD",
				"source":"1"
			},
			{
				"time":"59684.47",
				"band":"g",
				"e_magnitude":"0.152092625",
				"magnitude":"19.58347556",
				"system":"AB",
				"u_time":"MJD",
				"source":"1"
			},
			{
				"time":"59684.471",
				"band":"g",
				"e_magnitude":"0.191398493",
				"magnitude":"19.4714336",
				"system":"AB",
				"u_time":"MJD",
				"source":"1"
			},
			{
				"time":"59685.186",
				"band":"g",
				"e_magnitude":"0.331068604",
				"magnitude":"19.99429033",
				"system":"AB",
				"u_time":"MJD",
				"source":"1"
			},
			{
				"time":"59685.228",
				"band":"r",
				"e_magnitude":"0.115814045",
				"magnitude":"19.20736155",
				"system":"AB",
				"u_time":"MJD",
				"source":"1"
			},
			{
				"time":"59685.235",
				"band":"r",
				"e_magnitude":"0.107864801",
				"magnitude":"19.280365",
				"system":"AB",
				"u_time":"MJD",
				"source":"1"
			},
			{
				"time":"59685.308",
				"band":"i",
				"e_magnitude":"0.211680269",
				"magnitude":"19.49076877",
				"system":"AB",
				"u_time":"MJD",
				"source":"1"
			},
			{
				"time":"59685.333",
				"band":"g",
				"e_magnitude":"0.185409152",
				"magnitude":"19.37797344",
				"system":"AB",
				"u_time":"MJD",
				"source":"1"
			},
			{
				"time":"59685.342",
				"band":"r",
				"e_magnitude":"0.090280065",
				"magnitude":"19.27478064",
				"system":"AB",
				"u_time":"MJD",
				"source":"1"
			},
			{
				"time":"59685.372",
				"band":"r",
				"e_magnitude":"0.176934803",
				"magnitude":"19.38451686",
				"system":"AB",
				"u_time":"MJD",
				"source":"1"
			},
			{
				"time":"59686.403",
				"band":"r",
				"e_magnitude":"0.18917001",
				"magnitude":"19.40527073",
				"system":"AB",
				"u_time":"MJD",
				"source":"1"
			},
			{
				"time":"59686.404",
				"band":"r",
				"e_magnitude":"0.184325143",
				"magnitude":"19.45691319",
				"system":"AB",
				"u_time":"MJD",
				"source":"1"
			},
			{
				"time":"59687.334",
				"band":"i",
				"e_magnitude":"0.136019944",
				"magnitude":"19.25141214",
				"system":"AB",
				"u_time":"MJD",
				"source":"1"
			},
			{
				"time":"59687.341",
				"band":"r",
				"e_magnitude":"0.092358857",
				"magnitude":"19.24206237",
				"system":"AB",
				"u_time":"MJD",
				"source":"1"
			},
			{
				"time":"59687.342",
				"band":"r",
				"e_magnitude":"0.102916277",
				"magnitude":"19.17384168",
				"system":"AB",
				"u_time":"MJD",
				"source":"1"
			},
			{
				"time":"59687.383",
				"band":"r",
				"e_magnitude":"0.079585683",
				"magnitude":"19.23836126",
				"system":"AB",
				"u_time":"MJD",
				"source":"1"
			},
			{
				"time":"59687.384",
				"band":"r",
				"e_magnitude":"0.113376346",
				"magnitude":"19.42584602",
				"system":"AB",
				"u_time":"MJD",
				"source":"1"
			},
			{
				"time":"59687.404",
				"band":"r",
				"e_magnitude":"0.122385401",
				"magnitude":"19.34241778",
				"system":"AB",
				"u_time":"MJD",
				"source":"1"
			},
			{
				"time":"59687.405",
				"band":"r",
				"e_magnitude":"0.080080672",
				"magnitude":"19.17032346",
				"system":"AB",
				"u_time":"MJD",
				"source":"1"
			},
			{
				"time":"59687.407",
				"band":"o",
				"e_magnitude":"0.230517743",
				"magnitude":"19.86913236",
				"system":"AB",
				"u_time":"MJD",
				"source":"1"
			},
			{
				"time":"59687.424",
				"band":"g",
				"e_magnitude":"0.162348102",
				"magnitude":"19.6091819",
				"system":"AB",
				"u_time":"MJD",
				"source":"1"
			},
			{
				"time":"59687.458",
				"band":"g",
				"e_magnitude":"0.138411072",
				"magnitude":"19.29557651",
				"system":"AB",
				"u_time":"MJD",
				"source":"1"
			},
			{
				"time":"59688.268",
				"band":"g",
				"e_magnitude":"0.112556489",
				"magnitude":"19.47726308",
				"system":"AB",
				"u_time":"MJD",
				"source":"1"
			},
			{
				"time":"59688.268",
				"band":"g",
				"e_magnitude":"0.210972676",
				"magnitude":"19.76329397",
				"system":"AB",
				"u_time":"MJD",
				"source":"1"
			},
			{
				"time":"59688.319",
				"band":"r",
				"e_magnitude":"0.109294564",
				"magnitude":"19.37824054",
				"system":"AB",
				"u_time":"MJD",
				"source":"1"
			},
			{
				"time":"59688.345",
				"band":"r",
				"e_magnitude":"0.102041434",
				"magnitude":"19.27757162",
				"system":"AB",
				"u_time":"MJD",
				"source":"1"
			},
			{
				"time":"59688.389",
				"band":"r",
				"e_magnitude":"0.100025318",
				"magnitude":"19.0580631",
				"system":"AB",
				"u_time":"MJD",
				"source":"1"
			},
			{
				"time":"59689.266",
				"band":"r",
				"e_magnitude":"0.098101323",
				"magnitude":"19.38544966",
				"system":"AB",
				"u_time":"MJD",
				"source":"1"
			},
			{
				"time":"59689.267",
				"band":"r",
				"e_magnitude":"0.083425856",
				"magnitude":"19.20011747",
				"system":"AB",
				"u_time":"MJD",
				"source":"1"
			},
			{
				"time":"59689.287",
				"band":"g",
				"e_magnitude":"0.1548433",
				"magnitude":"19.78269416",
				"system":"AB",
				"u_time":"MJD",
				"source":"1"
			},
			{
				"time":"59689.398",
				"band":"r",
				"e_magnitude":"0.119993526",
				"magnitude":"19.29669182",
				"system":"AB",
				"u_time":"MJD",
				"source":"1"
			},
			{
				"time":"59689.436",
				"band":"r",
				"e_magnitude":"0.121408366",
				"magnitude":"19.38731994",
				"system":"AB",
				"u_time":"MJD",
				"source":"1"
			},
			{
				"time":"59689.453",
				"band":"o",
				"e_magnitude":"0.268615925",
				"magnitude":"19.72520946",
				"system":"AB",
				"u_time":"MJD",
				"source":"1"
			},
			{
				"time":"59690.244",
				"band":"r",
				"e_magnitude":"0.067369606",
				"magnitude":"19.36062229",
				"system":"AB",
				"u_time":"MJD",
				"source":"1"
			},
			{
				"time":"59690.287",
				"band":"g",
				"e_magnitude":"0.077237478",
				"magnitude":"19.86711102",
				"system":"AB",
				"u_time":"MJD",
				"source":"1"
			},
			{
				"time":"59690.307",
				"band":"g",
				"e_magnitude":"0.094889678",
				"magnitude":"19.81005094",
				"system":"AB",
				"u_time":"MJD",
				"source":"1"
			},
			{
				"time":"59690.308",
				"band":"g",
				"e_magnitude":"0.074103481",
				"magnitude":"19.62931173",
				"system":"AB",
				"u_time":"MJD",
				"source":"1"
			},
			{
				"time":"59690.308",
				"band":"g",
				"e_magnitude":"0.077010017",
				"magnitude":"19.78403852",
				"system":"AB",
				"u_time":"MJD",
				"source":"1"
			},
			{
				"time":"59690.325",
				"band":"r",
				"e_magnitude":"0.059863398",
				"magnitude":"19.23411265",
				"system":"AB",
				"u_time":"MJD",
				"source":"1"
			},
			{
				"time":"59690.325",
				"band":"r",
				"e_magnitude":"0.072511833",
				"magnitude":"19.29795626",
				"system":"AB",
				"u_time":"MJD",
				"source":"1"
			},
			{
				"time":"59690.344",
				"band":"r",
				"e_magnitude":"0.065499976",
				"magnitude":"19.19386193",
				"system":"AB",
				"u_time":"MJD",
				"source":"1"
			},
			{
				"time":"59690.346",
				"band":"r",
				"e_magnitude":"0.062127586",
				"magnitude":"19.2148928",
				"system":"AB",
				"u_time":"MJD",
				"source":"1"
			},
			{
				"time":"59690.384",
				"band":"i",
				"e_magnitude":"0.172564892",
				"magnitude":"19.52328009",
				"system":"AB",
				"u_time":"MJD",
				"source":"1"
			},
			{
				"time":"59690.413",
				"band":"i",
				"e_magnitude":"0.117160188",
				"magnitude":"19.34907326",
				"system":"AB",
				"u_time":"MJD",
				"source":"1"
			},
			{
				"time":"59690.444",
				"band":"g",
				"e_magnitude":"0.124456449",
				"magnitude":"19.72232744",
				"system":"AB",
				"u_time":"MJD",
				"source":"1"
			},
			{
				"time":"59690.444",
				"band":"g",
				"e_magnitude":"0.138204404",
				"magnitude":"19.92029456",
				"system":"AB",
				"u_time":"MJD",
				"source":"1"
			},
			{
				"time":"59690.467",
				"band":"r",
				"e_magnitude":"0.073927736",
				"magnitude":"19.18610866",
				"system":"AB",
				"u_time":"MJD",
				"source":"1"
			},
			{
				"time":"59693.26",
				"band":"r",
				"e_magnitude":"0.075668571",
				"magnitude":"19.4616398",
				"system":"AB",
				"u_time":"MJD",
				"source":"1"
			},
			{
				"time":"59693.261",
				"band":"r",
				"e_magnitude":"0.056717132",
				"magnitude":"19.22880704",
				"system":"AB",
				"u_time":"MJD",
				"source":"1"
			},
			{
				"time":"59693.304",
				"band":"r",
				"e_magnitude":"0.057477054",
				"magnitude":"19.19851265",
				"system":"AB",
				"u_time":"MJD",
				"source":"1"
			},
			{
				"time":"59693.305",
				"band":"r",
				"e_magnitude":"0.083806392",
				"magnitude":"19.31396148",
				"system":"AB",
				"u_time":"MJD",
				"source":"1"
			},
			{
				"time":"59693.349",
				"band":"g",
				"e_magnitude":"0.08723372",
				"magnitude":"19.82803874",
				"system":"AB",
				"u_time":"MJD",
				"source":"1"
			},
			{
				"time":"59693.349",
				"band":"g",
				"e_magnitude":"0.123992598",
				"magnitude":"19.99589902",
				"system":"AB",
				"u_time":"MJD",
				"source":"1"
			},
			{
				"time":"59693.371",
				"band":"i",
				"e_magnitude":"0.127885569",
				"magnitude":"19.23974067",
				"system":"AB",
				"u_time":"MJD",
				"source":"1"
			},
			{
				"time":"59693.395",
				"band":"i",
				"e_magnitude":"0.116567493",
				"magnitude":"19.52606234",
				"system":"AB",
				"u_time":"MJD",
				"source":"1"
			},
			{
				"time":"59693.399",
				"band":"o",
				"e_magnitude":"0.220300923",
				"magnitude":"19.39596732",
				"system":"AB",
				"u_time":"MJD",
				"source":"1"
			},
			{
				"time":"59693.443",
				"band":"g",
				"e_magnitude":"0.123948565",
				"magnitude":"20.00730219",
				"system":"AB",
				"u_time":"MJD",
				"source":"1"
			},
			{
				"time":"59693.468",
				"band":"g",
				"e_magnitude":"0.145930889",
				"magnitude":"19.74163683",
				"system":"AB",
				"u_time":"MJD",
				"source":"1"
			},
			{
				"time":"59694.243",
				"band":"r",
				"e_magnitude":"0.073918099",
				"magnitude":"19.41873529",
				"system":"AB",
				"u_time":"MJD",
				"source":"1"
			},
			{
				"time":"59694.281",
				"band":"r",
				"e_magnitude":"0.055765131",
				"magnitude":"19.27744312",
				"system":"AB",
				"u_time":"MJD",
				"source":"1"
			},
			{
				"time":"59694.284",
				"band":"r",
				"e_magnitude":"0.055372681",
				"magnitude":"19.35265882",
				"system":"AB",
				"u_time":"MJD",
				"source":"1"
			},
			{
				"time":"59694.308",
				"band":"r",
				"e_magnitude":"0.051856113",
				"magnitude":"19.27057202",
				"system":"AB",
				"u_time":"MJD",
				"source":"1"
			},
			{
				"time":"59694.308",
				"band":"r",
				"e_magnitude":"0.061025679",
				"magnitude":"19.39106645",
				"system":"AB",
				"u_time":"MJD",
				"source":"1"
			},
			{
				"time":"59694.309",
				"band":"r",
				"e_magnitude":"0.060257002",
				"magnitude":"19.37657618",
				"system":"AB",
				"u_time":"MJD",
				"source":"1"
			},
			{
				"time":"59694.368",
				"band":"g",
				"e_magnitude":"0.084889964",
				"magnitude":"20.03190264",
				"system":"AB",
				"u_time":"MJD",
				"source":"1"
			},
			{
				"time":"59694.369",
				"band":"g",
				"e_magnitude":"0.111205193",
				"magnitude":"20.12912051",
				"system":"AB",
				"u_time":"MJD",
				"source":"1"
			},
			{
				"time":"59694.385",
				"band":"g",
				"e_magnitude":"0.094998766",
				"magnitude":"19.9728784",
				"system":"AB",
				"u_time":"MJD",
				"source":"1"
			},
			{
				"time":"59694.393",
				"band":"g",
				"e_magnitude":"0.129137063",
				"magnitude":"19.89264511",
				"system":"AB",
				"u_time":"MJD",
				"source":"1"
			},
			{
				"time":"59694.407",
				"band":"g",
				"e_magnitude":"0.144743449",
				"magnitude":"20.07082175",
				"system":"AB",
				"u_time":"MJD",
				"source":"1"
			},
			{
				"time":"59694.41",
				"band":"g",
				"e_magnitude":"0.123715071",
				"magnitude":"20.0084299",
				"system":"AB",
				"u_time":"MJD",
				"source":"1"
			},
			{
				"time":"59695.248",
				"band":"r",
				"e_magnitude":"0.124633883",
				"magnitude":"19.25555375",
				"system":"AB",
				"u_time":"MJD",
				"source":"1"
			},
			{
				"time":"59695.31",
				"band":"r",
				"e_magnitude":"0.104258808",
				"magnitude":"19.37502433",
				"system":"AB",
				"u_time":"MJD",
				"source":"1"
			},
			{
				"time":"59695.339",
				"band":"g",
				"e_magnitude":"0.277719927",
				"magnitude":"19.93794066",
				"system":"AB",
				"u_time":"MJD",
				"source":"1"
			},
			{
				"time":"59695.342",
				"band":"g",
				"e_magnitude":"0.309112368",
				"magnitude":"20.1444793",
				"system":"AB",
				"u_time":"MJD",
				"source":"1"
			},
			{
				"time":"59695.372",
				"band":"c",
				"e_magnitude":"0.125181604",
				"magnitude":"19.75790223",
				"system":"AB",
				"u_time":"MJD",
				"source":"1"
			},
			{
				"time":"59695.413",
				"band":"r",
				"e_magnitude":"0.139917475",
				"magnitude":"19.3252177",
				"system":"AB",
				"u_time":"MJD",
				"source":"1"
			},
			{
				"time":"59696.198",
				"band":"g",
				"e_magnitude":"0.071574933",
				"magnitude":"19.90380508",
				"system":"AB",
				"u_time":"MJD",
				"source":"1"
			},
			{
				"time":"59696.222",
				"band":"g",
				"e_magnitude":"0.128032776",
				"magnitude":"20.2121132",
				"system":"AB",
				"u_time":"MJD",
				"source":"1"
			},
			{
				"time":"59696.223",
				"band":"g",
				"e_magnitude":"0.121017986",
				"magnitude":"20.1596822",
				"system":"AB",
				"u_time":"MJD",
				"source":"1"
			},
			{
				"time":"59696.225",
				"band":"g",
				"e_magnitude":"0.093600967",
				"magnitude":"20.09993719",
				"system":"AB",
				"u_time":"MJD",
				"source":"1"
			},
			{
				"time":"59696.236",
				"band":"r",
				"e_magnitude":"0.065766389",
				"magnitude":"19.50760846",
				"system":"AB",
				"u_time":"MJD",
				"source":"1"
			},
			{
				"time":"59696.267",
				"band":"r",
				"e_magnitude":"0.1608279",
				"magnitude":"19.58267908",
				"system":"AB",
				"u_time":"MJD",
				"source":"1"
			},
			{
				"time":"59696.307",
				"band":"i",
				"e_magnitude":"0.115546147",
				"magnitude":"19.39906713",
				"system":"AB",
				"u_time":"MJD",
				"source":"1"
			},
			{
				"time":"59696.307",
				"band":"i",
				"e_magnitude":"0.135054342",
				"magnitude":"19.47347496",
				"system":"AB",
				"u_time":"MJD",
				"source":"1"
			},
			{
				"time":"59696.451",
				"band":"r",
				"e_magnitude":"0.056777397",
				"magnitude":"19.42685495",
				"system":"AB",
				"u_time":"MJD",
				"source":"1"
			},
			{
				"time":"59697.226",
				"band":"g",
				"e_magnitude":"0.098105262",
				"magnitude":"20.17020334",
				"system":"AB",
				"u_time":"MJD",
				"source":"1"
			},
			{
				"time":"59697.259",
				"band":"g",
				"e_magnitude":"0.07968044",
				"magnitude":"20.08596684",
				"system":"AB",
				"u_time":"MJD",
				"source":"1"
			},
			{
				"time":"59697.302",
				"band":"r",
				"e_magnitude":"0.04908145",
				"magnitude":"19.39627463",
				"system":"AB",
				"u_time":"MJD",
				"source":"1"
			},
			{
				"time":"59697.303",
				"band":"r",
				"e_magnitude":"0.059742709",
				"magnitude":"19.5322086",
				"system":"AB",
				"u_time":"MJD",
				"source":"1"
			},
			{
				"time":"59697.363",
				"band":"r",
				"e_magnitude":"0.122666231",
				"magnitude":"19.6780151",
				"system":"AB",
				"u_time":"MJD",
				"source":"1"
			},
			{
				"time":"59697.385",
				"band":"r",
				"e_magnitude":"0.04691834",
				"magnitude":"19.30686829",
				"system":"AB",
				"u_time":"MJD",
				"source":"1"
			},
			{
				"time":"59697.423",
				"band":"g",
				"e_magnitude":"0.159893732",
				"magnitude":"20.85513727",
				"system":"AB",
				"u_time":"MJD",
				"source":"1"
			},
			{
				"time":"59697.447",
				"band":"g",
				"e_magnitude":"0.09063582",
				"magnitude":"20.1653111",
				"system":"AB",
				"u_time":"MJD",
				"source":"1"
			},
			{
				"time":"59697.486",
				"band":"o",
				"e_magnitude":"0.18042938",
				"magnitude":"19.50268882",
				"system":"AB",
				"u_time":"MJD",
				"source":"1"
			},
			{
				"time":"59698.334",
				"band":"g",
				"e_magnitude":"0.107703928",
				"magnitude":"20.26499899",
				"system":"AB",
				"u_time":"MJD",
				"source":"1"
			},
			{
				"time":"59698.372",
				"band":"r",
				"e_magnitude":"0.076463401",
				"magnitude":"19.63290053",
				"system":"AB",
				"u_time":"MJD",
				"source":"1"
			},
			{
				"time":"59698.373",
				"band":"r",
				"e_magnitude":"0.074422508",
				"magnitude":"19.62947061",
				"system":"AB",
				"u_time":"MJD",
				"source":"1"
			},
			{
				"time":"59698.374",
				"band":"r",
				"e_magnitude":"0.065647404",
				"magnitude":"19.39971467",
				"system":"AB",
				"u_time":"MJD",
				"source":"1"
			},
			{
				"time":"59698.375",
				"band":"r",
				"e_magnitude":"0.065225523",
				"magnitude":"19.4413389",
				"system":"AB",
				"u_time":"MJD",
				"source":"1"
			},
			{
				"time":"59698.383",
				"band":"r",
				"e_magnitude":"0.0724433",
				"magnitude":"19.49457901",
				"system":"AB",
				"u_time":"MJD",
				"source":"1"
			},
			{
				"time":"59698.384",
				"band":"r",
				"e_magnitude":"0.063320777",
				"magnitude":"19.41515407",
				"system":"AB",
				"u_time":"MJD",
				"source":"1"
			},
			{
				"time":"59699.229",
				"band":"g",
				"e_magnitude":"0.12273403",
				"magnitude":"20.21840827",
				"system":"AB",
				"u_time":"MJD",
				"source":"1"
			},
			{
				"time":"59699.275",
				"band":"r",
				"e_magnitude":"0.055817651",
				"magnitude":"19.30886729",
				"system":"AB",
				"u_time":"MJD",
				"source":"1"
			},
			{
				"time":"59699.361",
				"band":"r",
				"e_magnitude":"0.071382334",
				"magnitude":"19.46245235",
				"system":"AB",
				"u_time":"MJD",
				"source":"1"
			},
			{
				"time":"59699.384",
				"band":"g",
				"e_magnitude":"0.090241088",
				"magnitude":"20.16508761",
				"system":"AB",
				"u_time":"MJD",
				"source":"1"
			},
			{
				"time":"59699.464",
				"band":"g",
				"e_magnitude":"0.100660335",
				"magnitude":"19.93841513",
				"system":"AB",
				"u_time":"MJD",
				"source":"1"
			},
			{
				"time":"59699.465",
				"band":"c",
				"e_magnitude":"0.313170686",
				"magnitude":"19.48182597",
				"system":"AB",
				"u_time":"MJD",
				"source":"1"
			},
			{
				"time":"59699.466",
				"band":"g",
				"e_magnitude":"0.123251744",
				"magnitude":"20.21798278",
				"system":"AB",
				"u_time":"MJD",
				"source":"1"
			},
			{
				"time":"59700.175",
				"band":"r",
				"e_magnitude":"0.051514857",
				"magnitude":"19.29002886",
				"system":"AB",
				"u_time":"MJD",
				"source":"1"
			},
			{
				"time":"59700.175",
				"band":"r",
				"e_magnitude":"0.073951751",
				"magnitude":"19.39450606",
				"system":"AB",
				"u_time":"MJD",
				"source":"1"
			},
			{
				"time":"59700.242",
				"band":"g",
				"e_magnitude":"0.086392023",
				"magnitude":"20.08895484",
				"system":"AB",
				"u_time":"MJD",
				"source":"1"
			},
			{
				"time":"59700.243",
				"band":"g",
				"e_magnitude":"0.08646476",
				"magnitude":"19.96958121",
				"system":"AB",
				"u_time":"MJD",
				"source":"1"
			},
			{
				"time":"59700.263",
				"band":"g",
				"e_magnitude":"0.098727199",
				"magnitude":"19.94430009",
				"system":"AB",
				"u_time":"MJD",
				"source":"1"
			},
			{
				"time":"59700.263",
				"band":"g",
				"e_magnitude":"0.088266389",
				"magnitude":"20.10673395",
				"system":"AB",
				"u_time":"MJD",
				"source":"1"
			},
			{
				"time":"59700.282",
				"band":"r",
				"e_magnitude":"0.061773212",
				"magnitude":"19.35310838",
				"system":"AB",
				"u_time":"MJD",
				"source":"1"
			},
			{
				"time":"59700.306",
				"band":"r",
				"e_magnitude":"0.042194579",
				"magnitude":"19.24377277",
				"system":"AB",
				"u_time":"MJD",
				"source":"1"
			},
			{
				"time":"59700.307",
				"band":"r",
				"e_magnitude":"0.059400277",
				"magnitude":"19.26492407",
				"system":"AB",
				"u_time":"MJD",
				"source":"1"
			},
			{
				"time":"59700.307",
				"band":"r",
				"e_magnitude":"0.050028678",
				"magnitude":"19.38197324",
				"system":"AB",
				"u_time":"MJD",
				"source":"1"
			},
			{
				"time":"59700.323",
				"band":"i",
				"e_magnitude":"0.095214751",
				"magnitude":"19.29204636",
				"system":"AB",
				"u_time":"MJD",
				"source":"1"
			},
			{
				"time":"59700.324",
				"band":"i",
				"e_magnitude":"0.084148439",
				"magnitude":"19.25321232",
				"system":"AB",
				"u_time":"MJD",
				"source":"1"
			},
			{
				"time":"59700.341",
				"band":"g",
				"e_magnitude":"0.094436576",
				"magnitude":"20.15648887",
				"system":"AB",
				"u_time":"MJD",
				"source":"1"
			},
			{
				"time":"59700.368",
				"band":"g",
				"e_magnitude":"0.076493057",
				"magnitude":"20.02237268",
				"system":"AB",
				"u_time":"MJD",
				"source":"1"
			},
			{
				"time":"59701.309",
				"band":"g",
				"e_magnitude":"0.06798736",
				"magnitude":"19.89412455",
				"system":"AB",
				"u_time":"MJD",
				"source":"1"
			},
			{
				"time":"59701.347",
				"band":"g",
				"e_magnitude":"0.094959572",
				"magnitude":"19.85093723",
				"system":"AB",
				"u_time":"MJD",
				"source":"1"
			},
			{
				"time":"59701.387",
				"band":"g",
				"e_magnitude":"0.091932975",
				"magnitude":"20.00333783",
				"system":"AB",
				"u_time":"MJD",
				"source":"1"
			},
			{
				"time":"59701.391",
				"band":"g",
				"e_magnitude":"0.065347887",
				"magnitude":"19.79020994",
				"system":"AB",
				"u_time":"MJD",
				"source":"1"
			},
			{
				"time":"59701.427",
				"band":"g",
				"e_magnitude":"0.058185599",
				"magnitude":"19.78513527",
				"system":"AB",
				"u_time":"MJD",
				"source":"1"
			},
			{
				"time":"59701.428",
				"band":"g",
				"e_magnitude":"0.085914951",
				"magnitude":"20.01776929",
				"system":"AB",
				"u_time":"MJD",
				"source":"1"
			},
			{
				"time":"59702.173",
				"band":"r",
				"e_magnitude":"0.078927149",
				"magnitude":"19.21811804",
				"system":"AB",
				"u_time":"MJD",
				"source":"1"
			},
			{
				"time":"59702.283",
				"band":"g",
				"e_magnitude":"0.053176972",
				"magnitude":"19.64394248",
				"system":"AB",
				"u_time":"MJD",
				"source":"1"
			},
			{
				"time":"59702.283",
				"band":"g",
				"e_magnitude":"0.080541632",
				"magnitude":"19.96243858",
				"system":"AB",
				"u_time":"MJD",
				"source":"1"
			},
			{
				"time":"59702.284",
				"band":"g",
				"e_magnitude":"0.069138861",
				"magnitude":"19.79106234",
				"system":"AB",
				"u_time":"MJD",
				"source":"1"
			},
			{
				"time":"59702.309",
				"band":"g",
				"e_magnitude":"0.054527895",
				"magnitude":"19.68055565",
				"system":"AB",
				"u_time":"MJD",
				"source":"1"
			},
			{
				"time":"59702.323",
				"band":"g",
				"e_magnitude":"0.065259369",
				"magnitude":"19.85679192",
				"system":"AB",
				"u_time":"MJD",
				"source":"1"
			},
			{
				"time":"59702.324",
				"band":"g",
				"e_magnitude":"0.047577486",
				"magnitude":"19.61015477",
				"system":"AB",
				"u_time":"MJD",
				"source":"1"
			},
			{
				"time":"59702.349",
				"band":"r",
				"e_magnitude":"0.051722815",
				"magnitude":"19.13186559",
				"system":"AB",
				"u_time":"MJD",
				"source":"1"
			},
			{
				"time":"59702.35",
				"band":"r",
				"e_magnitude":"0.042476142",
				"magnitude":"19.04951438",
				"system":"AB",
				"u_time":"MJD",
				"source":"1"
			},
			{
				"time":"59702.35",
				"band":"r",
				"e_magnitude":"0.039798601",
				"magnitude":"19.09030449",
				"system":"AB",
				"u_time":"MJD",
				"source":"1"
			},
			{
				"time":"59702.363",
				"band":"r",
				"e_magnitude":"0.048717339",
				"magnitude":"19.14563238",
				"system":"AB",
				"u_time":"MJD",
				"source":"1"
			},
			{
				"time":"59702.364",
				"band":"r",
				"e_magnitude":"0.0378793",
				"magnitude":"19.04746105",
				"system":"AB",
				"u_time":"MJD",
				"source":"1"
			},
			{
				"time":"59707.225",
				"band":"r",
				"e_magnitude":"0.027074944",
				"magnitude":"18.28901259",
				"system":"AB",
				"u_time":"MJD",
				"source":"1"
			},
			{
				"time":"59707.267",
				"band":"r",
				"e_magnitude":"0.031197362",
				"magnitude":"18.37641355",
				"system":"AB",
				"u_time":"MJD",
				"source":"1"
			},
			{
				"time":"59707.279",
				"band":"r",
				"e_magnitude":"0.030606275",
				"magnitude":"18.30211354",
				"system":"AB",
				"u_time":"MJD",
				"source":"1"
			},
			{
				"time":"59707.281",
				"band":"r",
				"e_magnitude":"0.030411424",
				"magnitude":"18.28747091",
				"system":"AB",
				"u_time":"MJD",
				"source":"1"
			},
			{
				"time":"59707.327",
				"band":"r",
				"e_magnitude":"0.036775677",
				"magnitude":"18.38916172",
				"system":"AB",
				"u_time":"MJD",
				"source":"1"
			},
			{
				"time":"59707.33",
				"band":"r",
				"e_magnitude":"0.02865852",
				"magnitude":"18.3365166",
				"system":"AB",
				"u_time":"MJD",
				"source":"1"
			},
			{
				"time":"59707.347",
				"band":"r",
				"e_magnitude":"0.025463594",
				"magnitude":"18.26680627",
				"system":"AB",
				"u_time":"MJD",
				"source":"1"
			},
			{
				"time":"59707.367",
				"band":"r",
				"e_magnitude":"0.029549023",
				"magnitude":"18.32375422",
				"system":"AB",
				"u_time":"MJD",
				"source":"1"
			},
			{
				"time":"59707.37",
				"band":"r",
				"e_magnitude":"0.036265014",
				"magnitude":"18.38077768",
				"system":"AB",
				"u_time":"MJD",
				"source":"1"
			},
			{
				"time":"59707.888",
				"band":"g'",
				"e_magnitude":"0.033",
				"magnitude":"18.511",
				"system":"AB",
				"u_time":"MJD",
				"source":"1"
			},
			{
				"time":"59707.889",
				"band":"r'",
				"e_magnitude":"0.056",
				"magnitude":"18.267",
				"system":"AB",
				"u_time":"MJD",
				"source":"1"
			},
			{
				"time":"59707.89",
				"band":"i'",
				"e_magnitude":"0.073",
				"magnitude":"18.351",
				"system":"AB",
				"u_time":"MJD",
				"source":"1"
			},
			{
				"time":"59707.891",
				"band":"z'",
				"e_magnitude":"0.101",
				"magnitude":"18.494",
				"system":"AB",
				"u_time":"MJD",
				"source":"1"
			},
			{
				"time":"59708.37",
				"band":"g'",
				"e_magnitude":"0.040674625",
				"magnitude":"18.49074294",
				"system":"AB",
				"u_time":"MJD",
				"source":"1"
			},
			{
				"time":"59708.373",
				"band":"r'",
				"e_magnitude":"0.031668404",
				"magnitude":"18.11032648",
				"system":"AB",
				"u_time":"MJD",
				"source":"1"
			},
			{
				"time":"59708.376",
				"band":"i'",
				"e_magnitude":"0.035342668",
				"magnitude":"18.10538923",
				"system":"AB",
				"u_time":"MJD",
				"source":"1"
			},
			{
				"time":"59709.31",
				"band":"r",
				"e_magnitude":"0.025850899",
				"magnitude":"18.02518695",
				"system":"AB",
				"u_time":"MJD",
				"source":"1"
			},
			{
				"time":"59709.312",
				"band":"r",
				"e_magnitude":"0.031096739",
				"magnitude":"18.14319614",
				"system":"AB",
				"u_time":"MJD",
				"source":"1"
			},
			{
				"time":"59709.324",
				"band":"r",
				"e_magnitude":"0.032605535",
				"magnitude":"18.08182015",
				"system":"AB",
				"u_time":"MJD",
				"source":"1"
			},
			{
				"time":"59709.349",
				"band":"r",
				"e_magnitude":"0.027527144",
				"magnitude":"18.04911295",
				"system":"AB",
				"u_time":"MJD",
				"source":"1"
			},
			{
				"time":"59709.385",
				"band":"r",
				"e_magnitude":"0.024080349",
				"magnitude":"18.00707585",
				"system":"AB",
				"u_time":"MJD",
				"source":"1"
			},
			{
				"time":"59709.408",
				"band":"r",
				"e_magnitude":"0.028281547",
				"magnitude":"17.99145599",
				"system":"AB",
				"u_time":"MJD",
				"source":"1"
			},
			{
				"time":"59709.437",
				"band":"o",
				"e_magnitude":"0.041708954",
				"magnitude":"18.1036031",
				"system":"AB",
				"u_time":"MJD",
				"source":"1"
			},
			{
				"time":"59710.322",
				"band":"g",
				"e_magnitude":"0.043046916",
				"magnitude":"18.35960939",
				"system":"AB",
				"u_time":"MJD",
				"source":"1"
			},
			{
				"time":"59710.323",
				"band":"g",
				"e_magnitude":"0.033056342",
				"magnitude":"18.29783129",
				"system":"AB",
				"u_time":"MJD",
				"source":"1"
			},
			{
				"time":"59711.015",
				"band":"g'",
				"e_magnitude":"0.037",
				"magnitude":"18.237",
				"system":"AB",
				"u_time":"MJD",
				"source":"1"
			},
			{
				"time":"59711.016",
				"band":"r'",
				"e_magnitude":"0.053",
				"magnitude":"18.035",
				"system":"AB",
				"u_time":"MJD",
				"source":"1"
			},
			{
				"time":"59711.017",
				"band":"i'",
				"e_magnitude":"0.077",
				"magnitude":"18.094",
				"system":"AB",
				"u_time":"MJD",
				"source":"1"
			},
			{
				"time":"59711.018",
				"band":"z'",
				"e_magnitude":"0.085",
				"magnitude":"18.33",
				"system":"AB",
				"u_time":"MJD",
				"source":"1"
			},
			{
				"time":"59711.217",
				"band":"g",
				"e_magnitude":"0.046489094",
				"magnitude":"18.16641038",
				"system":"AB",
				"u_time":"MJD",
				"source":"1"
			},
			{
				"time":"59711.246",
				"band":"g",
				"e_magnitude":"0.031615652",
				"magnitude":"18.25929533",
				"system":"AB",
				"u_time":"MJD",
				"source":"1"
			},
			{
				"time":"59711.345",
				"band":"r",
				"e_magnitude":"0.040811883",
				"magnitude":"17.94344488",
				"system":"AB",
				"u_time":"MJD",
				"source":"1"
			},
			{
				"time":"59711.346",
				"band":"r",
				"e_magnitude":"0.032909539",
				"magnitude":"17.94656006",
				"system":"AB",
				"u_time":"MJD",
				"source":"1"
			},
			{
				"time":"59711.366",
				"band":"r",
				"e_magnitude":"0.035097816",
				"magnitude":"18.01461172",
				"system":"AB",
				"u_time":"MJD",
				"source":"1"
			},
			{
				"time":"59711.369",
				"band":"r",
				"e_magnitude":"0.031204915",
				"magnitude":"17.96081063",
				"system":"AB",
				"u_time":"MJD",
				"source":"1"
			},
			{
				"time":"59711.442",
				"band":"o",
				"e_magnitude":"0.063450334",
				"magnitude":"18.00711188",
				"system":"AB",
				"u_time":"MJD",
				"source":"1"
			},
			{
				"time":"59712.283",
				"band":"g",
				"e_magnitude":"0.04323558",
				"magnitude":"18.19448407",
				"system":"AB",
				"u_time":"MJD",
				"source":"1"
			},
			{
				"time":"59712.304",
				"band":"i",
				"e_magnitude":"0.038596457",
				"magnitude":"18.05430407",
				"system":"AB",
				"u_time":"MJD",
				"source":"1"
			},
			{
				"time":"59712.305",
				"band":"i",
				"e_magnitude":"0.050917348",
				"magnitude":"17.94917199",
				"system":"AB",
				"u_time":"MJD",
				"source":"1"
			},
			{
				"time":"59712.341",
				"band":"r",
				"e_magnitude":"0.038665031",
				"magnitude":"17.94505907",
				"system":"AB",
				"u_time":"MJD",
				"source":"1"
			},
			{
				"time":"59713.229",
				"band":"r'",
				"e_magnitude":"0.043011039",
				"magnitude":"17.90008423",
				"system":"AB",
				"u_time":"MJD",
				"source":"1"
			},
			{
				"time":"59713.261",
				"band":"g'",
				"e_magnitude":"0.078611449",
				"magnitude":"18.21128272",
				"system":"AB",
				"u_time":"MJD",
				"source":"1"
			},
			{
				"time":"59713.264",
				"band":"r'",
				"e_magnitude":"0.03290583",
				"magnitude":"17.8999656",
				"system":"AB",
				"u_time":"MJD",
				"source":"1"
			},
			{
				"time":"59713.266",
				"band":"r",
				"e_magnitude":"0.035503487",
				"magnitude":"17.96031042",
				"system":"AB",
				"u_time":"MJD",
				"source":"1"
			},
			{
				"time":"59713.267",
				"band":"i'",
				"e_magnitude":"0.038892774",
				"magnitude":"17.93896508",
				"system":"AB",
				"u_time":"MJD",
				"source":"1"
			},
			{
				"time":"59713.268",
				"band":"r",
				"e_magnitude":"0.034911932",
				"magnitude":"17.92356612",
				"system":"AB",
				"u_time":"MJD",
				"source":"1"
			},
			{
				"time":"59713.269",
				"band":"r",
				"e_magnitude":"0.024742531",
				"magnitude":"17.79967692",
				"system":"AB",
				"u_time":"MJD",
				"source":"1"
			},
			{
				"time":"59713.409",
				"band":"o",
				"e_magnitude":"0.072309356",
				"magnitude":"17.9101445",
				"system":"AB",
				"u_time":"MJD",
				"source":"1"
			},
			{
				"time":"59714.341",
				"band":"r",
				"e_magnitude":"0.0362775",
				"magnitude":"17.97484039",
				"system":"AB",
				"u_time":"MJD",
				"source":"1"
			},
			{
				"time":"59715.271",
				"band":"g",
				"e_magnitude":"0.066836488",
				"magnitude":"18.25639759",
				"system":"AB",
				"u_time":"MJD",
				"source":"1"
			},
			{
				"time":"59715.281",
				"band":"g",
				"e_magnitude":"0.048688464",
				"magnitude":"18.35377179",
				"system":"AB",
				"u_time":"MJD",
				"source":"1"
			},
			{
				"time":"59715.425",
				"band":"o",
				"e_magnitude":"0.054073856",
				"magnitude":"18.06241307",
				"system":"AB",
				"u_time":"MJD",
				"source":"1"
			},
			{
				"time":"59717.218",
				"band":"r",
				"e_magnitude":"0.02277898",
				"magnitude":"17.92762454",
				"system":"AB",
				"u_time":"MJD",
				"source":"1"
			},
			{
				"time":"59717.219",
				"band":"r",
				"e_magnitude":"0.018484987",
				"magnitude":"17.92355963",
				"system":"AB",
				"u_time":"MJD",
				"source":"1"
			},
			{
				"time":"59717.219",
				"band":"r",
				"e_magnitude":"0.024855739",
				"magnitude":"17.94377353",
				"system":"AB",
				"u_time":"MJD",
				"source":"1"
			},
			{
				"time":"59717.361",
				"band":"i",
				"e_magnitude":"0.049551398",
				"magnitude":"17.97233697",
				"system":"AB",
				"u_time":"MJD",
				"source":"1"
			},
			{
				"time":"59717.369",
				"band":"i",
				"e_magnitude":"0.04378435",
				"magnitude":"18.10257539",
				"system":"AB",
				"u_time":"MJD",
				"source":"1"
			},
			{
				"time":"59717.415",
				"band":"o",
				"e_magnitude":"0.06718478",
				"magnitude":"18.00252688",
				"system":"AB",
				"u_time":"MJD",
				"source":"1"
			},
			{
				"time":"59718.223",
				"band":"r",
				"e_magnitude":"0.020758487",
				"magnitude":"18.02352244",
				"system":"AB",
				"u_time":"MJD",
				"source":"1"
			},
			{
				"time":"59718.224",
				"band":"r",
				"e_magnitude":"0.018710798",
				"magnitude":"18.0202905",
				"system":"AB",
				"u_time":"MJD",
				"source":"1"
			},
			{
				"time":"59718.259",
				"band":"r",
				"e_magnitude":"0.019305919",
				"magnitude":"18.00612176",
				"system":"AB",
				"u_time":"MJD",
				"source":"1"
			},
			{
				"time":"59718.262",
				"band":"r",
				"e_magnitude":"0.028412578",
				"magnitude":"18.06605089",
				"system":"AB",
				"u_time":"MJD",
				"source":"1"
			},
			{
				"time":"59718.406",
				"band":"r'",
				"e_magnitude":"0.050383165",
				"magnitude":"18.0641971",
				"system":"AB",
				"u_time":"MJD",
				"source":"1"
			},
			{
				"time":"59718.927",
				"band":"g'",
				"e_magnitude":"0.031843482",
				"magnitude":"18.5726076",
				"system":"AB",
				"u_time":"MJD",
				"source":"1"
			},
			{
				"time":"59718.928",
				"band":"r'",
				"e_magnitude":"0.063815221",
				"magnitude":"18.17749934",
				"system":"AB",
				"u_time":"MJD",
				"source":"1"
			},
			{
				"time":"59718.929",
				"band":"i'",
				"e_magnitude":"0.063819352",
				"magnitude":"18.16627984",
				"system":"AB",
				"u_time":"MJD",
				"source":"1"
			},
			{
				"time":"59718.93",
				"band":"z'",
				"e_magnitude":"0.084816695",
				"magnitude":"18.38002691",
				"system":"AB",
				"u_time":"MJD",
				"source":"1"
			},
			{
				"time":"59719.182",
				"band":"r'",
				"e_magnitude":"0.074030176",
				"magnitude":"18.08323031",
				"system":"AB",
				"u_time":"MJD",
				"source":"1"
			},
			{
				"time":"59719.215",
				"band":"g'",
				"e_magnitude":"0.05349956",
				"magnitude":"18.65950178",
				"system":"AB",
				"u_time":"MJD",
				"source":"1"
			},
			{
				"time":"59719.217",
				"band":"r'",
				"e_magnitude":"0.024398381",
				"magnitude":"18.1059677",
				"system":"AB",
				"u_time":"MJD",
				"source":"1"
			},
			{
				"time":"59719.22",
				"band":"i'",
				"e_magnitude":"0.027297489",
				"magnitude":"17.94469619",
				"system":"AB",
				"u_time":"MJD",
				"source":"1"
			},
			{
				"time":"59719.264",
				"band":"r",
				"e_magnitude":"0.022812691",
				"magnitude":"18.13031998",
				"system":"AB",
				"u_time":"MJD",
				"source":"1"
			},
			{
				"time":"59719.265",
				"band":"r",
				"e_magnitude":"0.020843026",
				"magnitude":"18.10616554",
				"system":"AB",
				"u_time":"MJD",
				"source":"1"
			},
			{
				"time":"59719.284",
				"band":"r",
				"e_magnitude":"0.017767601",
				"magnitude":"18.05226962",
				"system":"AB",
				"u_time":"MJD",
				"source":"1"
			},
			{
				"time":"59719.285",
				"band":"r",
				"e_magnitude":"0.01920685",
				"magnitude":"18.0963989",
				"system":"AB",
				"u_time":"MJD",
				"source":"1"
			},
			{
				"time":"59719.302",
				"band":"r",
				"e_magnitude":"0.019562548",
				"magnitude":"18.07057008",
				"system":"AB",
				"u_time":"MJD",
				"source":"1"
			},
			{
				"time":"59719.304",
				"band":"r",
				"e_magnitude":"0.019321493",
				"magnitude":"18.05631451",
				"system":"AB",
				"u_time":"MJD",
				"source":"1"
			},
			{
				"time":"59719.305",
				"band":"r",
				"e_magnitude":"0.023452823",
				"magnitude":"18.15508557",
				"system":"AB",
				"u_time":"MJD",
				"source":"1"
			},
			{
				"time":"59719.306",
				"band":"r",
				"e_magnitude":"0.027256903",
				"magnitude":"18.17647664",
				"system":"AB",
				"u_time":"MJD",
				"source":"1"
			},
			{
				"time":"59720.38",
				"band":"r'",
				"e_magnitude":"0.087273651",
				"magnitude":"18.21924968",
				"system":"AB",
				"u_time":"MJD",
				"source":"1"
			},
			{
				"time":"59720.381",
				"band":"i'",
				"e_magnitude":"0.096997106",
				"magnitude":"18.33194155",
				"system":"AB",
				"u_time":"MJD",
				"source":"1"
			},
			{
				"time":"59721.307",
				"band":"r",
				"e_magnitude":"0.020891474",
				"magnitude":"18.15146848",
				"system":"AB",
				"u_time":"MJD",
				"source":"1"
			},
			{
				"time":"59721.313",
				"band":"r",
				"e_magnitude":"0.019124285",
				"magnitude":"18.08564249",
				"system":"AB",
				"u_time":"MJD",
				"source":"1"
			},
			{
				"time":"59721.378",
				"band":"r'",
				"e_magnitude":"0.10107007",
				"magnitude":"18.42789337",
				"system":"AB",
				"u_time":"MJD",
				"source":"1"
			},
			{
				"time":"59721.379",
				"band":"i'",
				"e_magnitude":"0.097892457",
				"magnitude":"18.18930207",
				"system":"AB",
				"u_time":"MJD",
				"source":"1"
			},
			{
				"time":"59721.393",
				"band":"o",
				"e_magnitude":"0.036124893",
				"magnitude":"18.23943599",
				"system":"AB",
				"u_time":"MJD",
				"source":"1"
			},
			{
				"time":"59722.322",
				"band":"g",
				"e_magnitude":"0.034860565",
				"magnitude":"18.84582882",
				"system":"AB",
				"u_time":"MJD",
				"source":"1"
			},
			{
				"time":"59722.323",
				"band":"g",
				"e_magnitude":"0.029444039",
				"magnitude":"18.81864176",
				"system":"AB",
				"u_time":"MJD",
				"source":"1"
			},
			{
				"time":"59722.323",
				"band":"g",
				"e_magnitude":"0.034395111",
				"magnitude":"18.83033294",
				"system":"AB",
				"u_time":"MJD",
				"source":"1"
			},
			{
				"time":"59722.326",
				"band":"g",
				"e_magnitude":"0.030941477",
				"magnitude":"18.86290418",
				"system":"AB",
				"u_time":"MJD",
				"source":"1"
			},
			{
				"time":"59722.35",
				"band":"g",
				"e_magnitude":"0.038156612",
				"magnitude":"18.78924695",
				"system":"AB",
				"u_time":"MJD",
				"source":"1"
			},
			{
				"time":"59722.363",
				"band":"g",
				"e_magnitude":"0.031839626",
				"magnitude":"18.86207804",
				"system":"AB",
				"u_time":"MJD",
				"source":"1"
			},
			{
				"time":"59722.368",
				"band":"g",
				"e_magnitude":"0.033626246",
				"magnitude":"18.77793342",
				"system":"AB",
				"u_time":"MJD",
				"source":"1"
			},
			{
				"time":"59722.376",
				"band":"r'",
				"e_magnitude":"0.070161871",
				"magnitude":"18.39459813",
				"system":"AB",
				"u_time":"MJD",
				"source":"1"
			},
			{
				"time":"59722.377",
				"band":"i'",
				"e_magnitude":"0.154919468",
				"magnitude":"18.42162686",
				"system":"AB",
				"u_time":"MJD",
				"source":"1"
			},
			{
				"time":"59722.408",
				"band":"g",
				"e_magnitude":"0.051144626",
				"magnitude":"18.88786925",
				"system":"AB",
				"u_time":"MJD",
				"source":"1"
			},
			{
				"time":"59722.41",
				"band":"g",
				"e_magnitude":"0.042633747",
				"magnitude":"18.84486691",
				"system":"AB",
				"u_time":"MJD",
				"source":"1"
			},
			{
				"time":"59722.411",
				"band":"g",
				"e_magnitude":"0.042388821",
				"magnitude":"18.76154759",
				"system":"AB",
				"u_time":"MJD",
				"source":"1"
			},
			{
				"time":"59723.2",
				"band":"r",
				"e_magnitude":"0.031219635",
				"magnitude":"18.21892178",
				"system":"AB",
				"u_time":"MJD",
				"source":"1"
			},
			{
				"time":"59723.201",
				"band":"r",
				"e_magnitude":"0.031744859",
				"magnitude":"18.18753747",
				"system":"AB",
				"u_time":"MJD",
				"source":"1"
			},
			{
				"time":"59723.227",
				"band":"i",
				"e_magnitude":"0.050978964",
				"magnitude":"18.17897196",
				"system":"AB",
				"u_time":"MJD",
				"source":"1"
			},
			{
				"time":"59723.227",
				"band":"i",
				"e_magnitude":"0.045010387",
				"magnitude":"18.21659929",
				"system":"AB",
				"u_time":"MJD",
				"source":"1"
			},
			{
				"time":"59723.264",
				"band":"g",
				"e_magnitude":"0.036809626",
				"magnitude":"18.8630876",
				"system":"AB",
				"u_time":"MJD",
				"source":"1"
			},
			{
				"time":"59723.268",
				"band":"g",
				"e_magnitude":"0.035735335",
				"magnitude":"19.05156983",
				"system":"AB",
				"u_time":"MJD",
				"source":"1"
			},
			{
				"time":"59723.37",
				"band":"r'",
				"e_magnitude":"0.082009762",
				"magnitude":"18.46656609",
				"system":"AB",
				"u_time":"MJD",
				"source":"1"
			},
			{
				"time":"59723.371",
				"band":"i'",
				"e_magnitude":"0.136406466",
				"magnitude":"18.35993061",
				"system":"AB",
				"u_time":"MJD",
				"source":"1"
			},
			{
				"time":"59723.395",
				"band":"c",
				"e_magnitude":"0.04152862",
				"magnitude":"18.54926613",
				"system":"AB",
				"u_time":"MJD",
				"source":"1"
			},
			{
				"time":"59724.303",
				"band":"r",
				"e_magnitude":"0.023530746",
				"magnitude":"18.30006341",
				"system":"AB",
				"u_time":"MJD",
				"source":"1"
			},
			{
				"time":"59724.304",
				"band":"r",
				"e_magnitude":"0.026879478",
				"magnitude":"18.33564793",
				"system":"AB",
				"u_time":"MJD",
				"source":"1"
			},
			{
				"time":"59724.306",
				"band":"r",
				"e_magnitude":"0.021555043",
				"magnitude":"18.27779244",
				"system":"AB",
				"u_time":"MJD",
				"source":"1"
			},
			{
				"time":"59724.307",
				"band":"r",
				"e_magnitude":"0.021186428",
				"magnitude":"18.27204321",
				"system":"AB",
				"u_time":"MJD",
				"source":"1"
			},
			{
				"time":"59724.329",
				"band":"g",
				"e_magnitude":"0.035241245",
				"magnitude":"19.04238452",
				"system":"AB",
				"u_time":"MJD",
				"source":"1"
			},
			{
				"time":"59724.33",
				"band":"g",
				"e_magnitude":"0.031563798",
				"magnitude":"18.93132061",
				"system":"AB",
				"u_time":"MJD",
				"source":"1"
			},
			{
				"time":"59724.33",
				"band":"g",
				"e_magnitude":"0.041795965",
				"magnitude":"19.00418552",
				"system":"AB",
				"u_time":"MJD",
				"source":"1"
			},
			{
				"time":"59724.331",
				"band":"g",
				"e_magnitude":"0.040865365",
				"magnitude":"18.97720015",
				"system":"AB",
				"u_time":"MJD",
				"source":"1"
			},
			{
				"time":"59725.244",
				"band":"r",
				"e_magnitude":"0.027133192",
				"magnitude":"18.33921226",
				"system":"AB",
				"u_time":"MJD",
				"source":"1"
			},
			{
				"time":"59725.287",
				"band":"g",
				"e_magnitude":"0.044057262",
				"magnitude":"19.10703595",
				"system":"AB",
				"u_time":"MJD",
				"source":"1"
			},
			{
				"time":"59725.303",
				"band":"g",
				"e_magnitude":"0.034485638",
				"magnitude":"19.0844315",
				"system":"AB",
				"u_time":"MJD",
				"source":"1"
			},
			{
				"time":"59725.33",
				"band":"r",
				"e_magnitude":"0.023783562",
				"magnitude":"18.34979089",
				"system":"AB",
				"u_time":"MJD",
				"source":"1"
			},
			{
				"time":"59725.365",
				"band":"o",
				"e_magnitude":"0.046645534",
				"magnitude":"18.47820553",
				"system":"AB",
				"u_time":"MJD",
				"source":"1"
			},
			{
				"time":"59726.259",
				"band":"i",
				"e_magnitude":"0.046780758",
				"magnitude":"18.36881667",
				"system":"AB",
				"u_time":"MJD",
				"source":"1"
			},
			{
				"time":"59726.301",
				"band":"g",
				"e_magnitude":"0.044521539",
				"magnitude":"19.31226581",
				"system":"AB",
				"u_time":"MJD",
				"source":"1"
			},
			{
				"time":"59726.302",
				"band":"g",
				"e_magnitude":"0.039550285",
				"magnitude":"19.17556197",
				"system":"AB",
				"u_time":"MJD",
				"source":"1"
			},
			{
				"time":"59726.303",
				"band":"g",
				"e_magnitude":"0.033950436",
				"magnitude":"19.22079476",
				"system":"AB",
				"u_time":"MJD",
				"source":"1"
			},
			{
				"time":"59726.307",
				"band":"g",
				"e_magnitude":"0.03952796",
				"magnitude":"19.26566145",
				"system":"AB",
				"u_time":"MJD",
				"source":"1"
			},
			{
				"time":"59726.347",
				"band":"r",
				"e_magnitude":"0.029268613",
				"magnitude":"18.40461827",
				"system":"AB",
				"u_time":"MJD",
				"source":"1"
			},
			{
				"time":"59726.348",
				"band":"r",
				"e_magnitude":"0.027323286",
				"magnitude":"18.44203994",
				"system":"AB",
				"u_time":"MJD",
				"source":"1"
			},
			{
				"time":"59726.363",
				"band":"r",
				"e_magnitude":"0.023574419",
				"magnitude":"18.40596679",
				"system":"AB",
				"u_time":"MJD",
				"source":"1"
			},
			{
				"time":"59726.364",
				"band":"r",
				"e_magnitude":"0.02405119",
				"magnitude":"18.40715926",
				"system":"AB",
				"u_time":"MJD",
				"source":"1"
			},
			{
				"time":"59727.196",
				"band":"r'",
				"e_magnitude":"0.074376811",
				"magnitude":"18.5935115",
				"system":"AB",
				"u_time":"MJD",
				"source":"1"
			},
			{
				"time":"59727.228",
				"band":"g'",
				"e_magnitude":"0.061746427",
				"magnitude":"19.46237311",
				"system":"AB",
				"u_time":"MJD",
				"source":"1"
			},
			{
				"time":"59727.231",
				"band":"r'",
				"e_magnitude":"0.033701096",
				"magnitude":"18.44172524",
				"system":"AB",
				"u_time":"MJD",
				"source":"1"
			},
			{
				"time":"59727.234",
				"band":"i'",
				"e_magnitude":"0.036798453",
				"magnitude":"18.2830374",
				"system":"AB",
				"u_time":"MJD",
				"source":"1"
			},
			{
				"time":"59727.238",
				"band":"r",
				"e_magnitude":"0.0461695",
				"magnitude":"18.48301387",
				"system":"AB",
				"u_time":"MJD",
				"source":"1"
			},
			{
				"time":"59727.243",
				"band":"r",
				"e_magnitude":"0.038093382",
				"magnitude":"18.37797918",
				"system":"AB",
				"u_time":"MJD",
				"source":"1"
			},
			{
				"time":"59727.286",
				"band":"g",
				"e_magnitude":"0.198138638",
				"magnitude":"19.07262042",
				"system":"AB",
				"u_time":"MJD",
				"source":"1"
			},
			{
				"time":"59727.367",
				"band":"c",
				"e_magnitude":"0.104143339",
				"magnitude":"18.84129093",
				"system":"AB",
				"u_time":"MJD",
				"source":"1"
			},
			{
				"time":"59729.376",
				"band":"o",
				"e_magnitude":"0.058620316",
				"magnitude":"18.69321507",
				"system":"AB",
				"u_time":"MJD",
				"source":"1"
			},
			{
				"time":"59729.384",
				"band":"g",
				"e_magnitude":"0.078015398",
				"magnitude":"19.619302",
				"system":"AB",
				"u_time":"MJD",
				"source":"1"
			},
			{
				"time":"59729.385",
				"band":"g",
				"e_magnitude":"0.117875063",
				"magnitude":"19.77892379",
				"system":"AB",
				"u_time":"MJD",
				"source":"1"
			},
			{
				"time":"59729.388",
				"band":"g",
				"e_magnitude":"0.107744062",
				"magnitude":"19.75820729",
				"system":"AB",
				"u_time":"MJD",
				"source":"1"
			},
			{
				"time":"59729.389",
				"band":"g",
				"e_magnitude":"0.090969676",
				"magnitude":"19.75240429",
				"system":"AB",
				"u_time":"MJD",
				"source":"1"
			},
			{
				"time":"59730.24",
				"band":"r",
				"e_magnitude":"0.039186721",
				"magnitude":"18.86801349",
				"system":"AB",
				"u_time":"MJD",
				"source":"1"
			},
			{
				"time":"59730.262",
				"band":"r",
				"e_magnitude":"0.028488453",
				"magnitude":"18.65900981",
				"system":"AB",
				"u_time":"MJD",
				"source":"1"
			},
			{
				"time":"59730.306",
				"band":"g",
				"e_magnitude":"0.052498171",
				"magnitude":"19.73488605",
				"system":"AB",
				"u_time":"MJD",
				"source":"1"
			},
			{
				"time":"59730.306",
				"band":"g",
				"e_magnitude":"0.084215027",
				"magnitude":"19.92744227",
				"system":"AB",
				"u_time":"MJD",
				"source":"1"
			},
			{
				"time":"59730.352",
				"band":"r'",
				"e_magnitude":"0.061984035",
				"magnitude":"18.87967197",
				"system":"AB",
				"u_time":"MJD",
				"source":"1"
			},
			{
				"time":"59730.384",
				"band":"g'",
				"e_magnitude":"0.050503384",
				"magnitude":"19.62543368",
				"system":"AB",
				"u_time":"MJD",
				"source":"1"
			},
			{
				"time":"59730.387",
				"band":"r'",
				"e_magnitude":"0.035595972",
				"magnitude":"18.82248495",
				"system":"AB",
				"u_time":"MJD",
				"source":"1"
			},
			{
				"time":"59730.39",
				"band":"i'",
				"e_magnitude":"0.035197152",
				"magnitude":"18.42063195",
				"system":"AB",
				"u_time":"MJD",
				"source":"1"
			},
			{
				"time":"59731.265",
				"band":"i",
				"e_magnitude":"0.072093424",
				"magnitude":"18.72552531",
				"system":"AB",
				"u_time":"MJD",
				"source":"1"
			},
			{
				"time":"59731.266",
				"band":"i",
				"e_magnitude":"0.04762021",
				"magnitude":"18.61909077",
				"system":"AB",
				"u_time":"MJD",
				"source":"1"
			},
			{
				"time":"59731.31",
				"band":"r",
				"e_magnitude":"0.033236199",
				"magnitude":"18.79544633",
				"system":"AB",
				"u_time":"MJD",
				"source":"1"
			},
			{
				"time":"59731.324",
				"band":"g",
				"e_magnitude":"0.109780677",
				"magnitude":"20.076137",
				"system":"AB",
				"u_time":"MJD",
				"source":"1"
			},
			{
				"time":"59731.325",
				"band":"g",
				"e_magnitude":"0.094620414",
				"magnitude":"19.82214483",
				"system":"AB",
				"u_time":"MJD",
				"source":"1"
			},
			{
				"time":"59731.329",
				"band":"g",
				"e_magnitude":"0.092770368",
				"magnitude":"19.91190128",
				"system":"AB",
				"u_time":"MJD",
				"source":"1"
			},
			{
				"time":"59731.412",
				"band":"c",
				"e_magnitude":"0.087018349",
				"magnitude":"19.31565622",
				"system":"AB",
				"u_time":"MJD",
				"source":"1"
			},
			{
				"time":"59732.219",
				"band":"r",
				"e_magnitude":"0.037597176",
				"magnitude":"18.95061487",
				"system":"AB",
				"u_time":"MJD",
				"source":"1"
			},
			{
				"time":"59732.279",
				"band":"g",
				"e_magnitude":"0.079511384",
				"magnitude":"20.02044151",
				"system":"AB",
				"u_time":"MJD",
				"source":"1"
			},
			{
				"time":"59733.253",
				"band":"r",
				"e_magnitude":"0.043183353",
				"magnitude":"19.08567393",
				"system":"AB",
				"u_time":"MJD",
				"source":"1"
			},
			{
				"time":"59733.359",
				"band":"o",
				"e_magnitude":"0.074771983",
				"magnitude":"19.23795632",
				"system":"AB",
				"u_time":"MJD",
				"source":"1"
			},
			{
				"time":"59734.228",
				"band":"r",
				"e_magnitude":"0.052104819",
				"magnitude":"19.0431322",
				"system":"AB",
				"u_time":"MJD",
				"source":"1"
			},
			{
				"time":"59734.282",
				"band":"i",
				"e_magnitude":"0.099894455",
				"magnitude":"18.84995019",
				"system":"AB",
				"u_time":"MJD",
				"source":"1"
			},
			{
				"time":"59734.283",
				"band":"i",
				"e_magnitude":"0.076187649",
				"magnitude":"18.85847516",
				"system":"AB",
				"u_time":"MJD",
				"source":"1"
			},
			{
				"time":"59734.302",
				"band":"g",
				"e_magnitude":"0.090474761",
				"magnitude":"20.17662736",
				"system":"AB",
				"u_time":"MJD",
				"source":"1"
			},
			{
				"time":"59734.305",
				"band":"r'",
				"e_magnitude":"0.129442884",
				"magnitude":"19.21279262",
				"system":"AB",
				"u_time":"MJD",
				"source":"1"
			},
			{
				"time":"59734.338",
				"band":"g'",
				"e_magnitude":"0.065181913",
				"magnitude":"20.05658356",
				"system":"AB",
				"u_time":"MJD",
				"source":"1"
			},
			{
				"time":"59734.34",
				"band":"r'",
				"e_magnitude":"0.036558809",
				"magnitude":"19.1757573",
				"system":"AB",
				"u_time":"MJD",
				"source":"1"
			},
			{
				"time":"59734.343",
				"band":"i'",
				"e_magnitude":"0.039482007",
				"magnitude":"18.788227",
				"system":"AB",
				"u_time":"MJD",
				"source":"1"
			},
			{
				"time":"59735.276",
				"band":"g",
				"e_magnitude":"0.117846638",
				"magnitude":"20.28581855",
				"system":"AB",
				"u_time":"MJD",
				"source":"1"
			},
			{
				"time":"59735.342",
				"band":"o",
				"e_magnitude":"0.088436823",
				"magnitude":"19.14989885",
				"system":"AB",
				"u_time":"MJD",
				"source":"1"
			},
			{
				"time":"59736.22",
				"band":"r",
				"e_magnitude":"0.045173811",
				"magnitude":"19.20697656",
				"system":"AB",
				"u_time":"MJD",
				"source":"1"
			},
			{
				"time":"59736.278",
				"band":"g",
				"e_magnitude":"0.129194133",
				"magnitude":"20.45716769",
				"system":"AB",
				"u_time":"MJD",
				"source":"1"
			},
			{
				"time":"59736.915",
				"band":"g'",
				"e_magnitude":"0.207232244",
				"magnitude":"20.84905257",
				"system":"AB",
				"u_time":"MJD",
				"source":"1"
			},
			{
				"time":"59736.916",
				"band":"r'",
				"e_magnitude":"0.079367042",
				"magnitude":"19.59154086",
				"system":"AB",
				"u_time":"MJD",
				"source":"1"
			},
			{
				"time":"59736.917",
				"band":"i'",
				"e_magnitude":"0.084174706",
				"magnitude":"19.22768147",
				"system":"AB",
				"u_time":"MJD",
				"source":"1"
			},
			{
				"time":"59736.918",
				"band":"z'",
				"e_magnitude":"0.160540333",
				"magnitude":"19.4137994",
				"system":"AB",
				"u_time":"MJD",
				"source":"1"
			},
			{
				"time":"59737.197",
				"band":"g",
				"e_magnitude":"0.133733109",
				"magnitude":"20.11282796",
				"system":"AB",
				"u_time":"MJD",
				"source":"1"
			},
			{
				"time":"59737.214",
				"band":"r",
				"e_magnitude":"0.059654623",
				"magnitude":"19.28792572",
				"system":"AB",
				"u_time":"MJD",
				"source":"1"
			},
			{
				"time":"59737.245",
				"band":"i",
				"e_magnitude":"0.077743879",
				"magnitude":"19.16561189",
				"system":"AB",
				"u_time":"MJD",
				"source":"1"
			},
			{
				"time":"59737.26",
				"band":"i",
				"e_magnitude":"0.070989781",
				"magnitude":"19.04415502",
				"system":"AB",
				"u_time":"MJD",
				"source":"1"
			},
			{
				"time":"59737.371",
				"band":"o",
				"e_magnitude":"0.113252961",
				"magnitude":"19.38388478",
				"system":"AB",
				"u_time":"MJD",
				"source":"1"
			},
			{
				"time":"59738.219",
				"band":"g",
				"e_magnitude":"0.254530933",
				"magnitude":"20.84513246",
				"system":"AB",
				"u_time":"MJD",
				"source":"1"
			},
			{
				"time":"59738.258",
				"band":"r",
				"e_magnitude":"0.075222832",
				"magnitude":"19.53775543",
				"system":"AB",
				"u_time":"MJD",
				"source":"1"
			},
			{
				"time":"59739.369",
				"band":"o",
				"e_magnitude":"0.189169954",
				"magnitude":"19.8766722",
				"system":"AB",
				"u_time":"MJD",
				"source":"1"
			},
			{
				"time":"59741.244",
				"band":"r'",
				"e_magnitude":"0.059846517",
				"magnitude":"19.57592384",
				"system":"AB",
				"u_time":"MJD",
				"source":"1"
			},
			{
				"time":"59741.247",
				"band":"i'",
				"e_magnitude":"0.066771572",
				"magnitude":"19.34494694",
				"system":"AB",
				"u_time":"MJD",
				"source":"1"
			},
			{
				"time":"59741.34",
				"band":"o",
				"e_magnitude":"0.277118502",
				"magnitude":"19.89547096",
				"system":"AB",
				"u_time":"MJD",
				"source":"1"
			},
			{
				"time":"59745.344",
				"band":"o",
				"e_magnitude":"0.273355231",
				"magnitude":"20.08910076",
				"system":"AB",
				"u_time":"MJD",
				"source":"1"
			},
			{
				"time":"59745.918",
				"band":"g'",
				"e_magnitude":"0.425739415",
				"magnitude":"21.23607942",
				"system":"AB",
				"u_time":"MJD",
				"source":"1"
			},
			{
				"time":"59745.919",
				"band":"r'",
				"e_magnitude":"0.169846093",
				"magnitude":"20.38920403",
				"system":"AB",
				"u_time":"MJD",
				"source":"1"
			},
			{
				"time":"59745.92",
				"band":"i'",
				"e_magnitude":"0.11182821",
				"magnitude":"19.81392824",
				"system":"AB",
				"u_time":"MJD",
				"source":"1"
			},
			{
				"time":"59745.922",
				"band":"z'",
				"e_magnitude":"0.171362758",
				"magnitude":"19.665259",
				"system":"AB",
				"u_time":"MJD",
				"source":"1"
			},
			{
				"time":"59748.338",
				"band":"g'",
				"e_magnitude":"0.150861637",
				"magnitude":"21.09588414",
				"system":"AB",
				"u_time":"MJD",
				"source":"1"
			},
			{
				"time":"59748.341",
				"band":"i'",
				"e_magnitude":"0.05950786",
				"magnitude":"19.60858391",
				"system":"AB",
				"u_time":"MJD",
				"source":"1"
			},
			{
				"time":"59749.338",
				"band":"o",
				"e_magnitude":"0.193793929",
				"magnitude":"20.29562604",
				"system":"AB",
				"u_time":"MJD",
				"source":"1"
			},
			{
				"time":"59751.323",
				"band":"c",
				"e_magnitude":"0.201470481",
				"magnitude":"20.45840072",
				"system":"AB",
				"u_time":"MJD",
				"source":"1"
			},
			{
				"time":"59757.309",
				"band":"o",
				"e_magnitude":"0.234180876",
				"magnitude":"20.2949463",
				"system":"AB",
				"u_time":"MJD",
				"source":"1"
			},
			{
				"time":"59758.935",
				"band":"g'",
				"e_magnitude":"0.417808657",
				"magnitude":"22.55450386",
				"system":"AB",
				"u_time":"MJD",
				"source":"1"
			},
			{
				"time":"59758.936",
				"band":"g'",
				"e_magnitude":"0.43436883",
				"magnitude":"22.55718168",
				"system":"AB",
				"u_time":"MJD",
				"source":"1"
			},
			{
				"time":"59758.937",
				"band":"r'",
				"e_magnitude":"0.112714458",
				"magnitude":"20.82838323",
				"system":"AB",
				"u_time":"MJD",
				"source":"1"
			},
			{
				"time":"59758.938",
				"band":"i'",
				"e_magnitude":"0.116161903",
				"magnitude":"20.41780035",
				"system":"AB",
				"u_time":"MJD",
				"source":"1"
			},
			{
				"time":"59758.939",
				"band":"z'",
				"e_magnitude":"0.156272551",
				"magnitude":"19.95680981",
				"system":"AB",
				"u_time":"MJD",
				"source":"1"
			},
			{
				"time":"59775.209",
				"band":"r'",
				"e_magnitude":"0.186423285",
				"magnitude":"20.48664497",
				"system":"AB",
				"u_time":"MJD",
				"source":"1"
			},
			{
				"time":"59784.915",
				"band":"g'",
				"e_magnitude":"0.317979842",
				"magnitude":"21.7230723",
				"system":"AB",
				"u_time":"MJD",
				"source":"1"
			},
			{
				"time":"59784.918",
				"band":"i'",
				"e_magnitude":"0.260083406",
				"magnitude":"21.00300404",
				"system":"AB",
				"u_time":"MJD",
				"source":"1"
			},
			{
				"time":"59784.919",
				"band":"z'",
				"e_magnitude":"0.256398065",
				"magnitude":"20.18387138",
				"system":"AB",
				"u_time":"MJD",
				"source":"1"
			}
		]
	}
}